README.txt
bootstrap.py
buildout.cfg
setup.py
docs/HISTORY.txt
src/munin/__init__.py
src/munin.plone.egg-info/PKG-INFO
src/munin.plone.egg-info/SOURCES.txt
src/munin.plone.egg-info/dependency_links.txt
src/munin.plone.egg-info/entry_points.txt
src/munin.plone.egg-info/namespace_packages.txt
src/munin.plone.egg-info/not-zip-safe
src/munin.plone.egg-info/requires.txt
src/munin.plone.egg-info/top_level.txt
src/munin/plone/__init__.py
src/munin/plone/browser.py
src/munin/plone/configure.zcml
src/munin/plone/plugins.py