Metadata-Version: 1.0
Name: munin.plone
Version: 1.0
Summary: Munin plugins for Plone.
Home-page: http://plone.org/products/munin.plone
Author: Andrew Mleczko
Author-email: andrew.mleczko@redturtle.it
License: GPL
Keywords: plone munin monitoring
Platform: Any
Classifier: Development Status :: 3 - Alpha
Classifier: Programming Language :: Python
Classifier: Framework :: Plone
Classifier: Intended Audience :: Developers
Classifier: Intended Audience :: System Administrators
Classifier: License :: OSI Approved :: GNU General Public License (GPL)
Classifier: Programming Language :: Python
Classifier: Topic :: System :: Networking :: Monitoring
Classifier: Topic :: Software Development :: Libraries :: Python Modules
